aioauthx/__init__.py
aioauthx/__version__.py
aioauthx/auth.py
aioauthx/client_reqrep.py
aioauthx/flows/__init__.py
aioauthx/flows/negotiate.py
aioauthx-0.1.1.dist-info/METADATA
aioauthx-0.1.1.dist-info/WHEEL
aioauthx-0.1.1.dist-info/licenses/LICENSE
aioauthx-0.1.1.dist-info/RECORD
