Metadata-Version: 2.1
Name: aioauthx
Version: 0.1.1
Summary: HTTPX-style authorization schemes for aiohttp.
Project-URL: Changelog, https://github.com/newvicx/aioauthx/blob/master/CHANGELOG.md
Project-URL: Homepage, https://github.com/newvicx/aioauthx
Project-URL: Source, https://github.com/newvicx/aioauthx
Author-email: Chris Newville <chrisnewville1396@gmail.com>
License-Expression: MIT
License-File: LICENSE
Classifier: Development Status :: 4 - Beta
Classifier: Intended Audience :: Developers
Classifier: License :: OSI Approved :: MIT License
Classifier: Operating System :: OS Independent
Classifier: Programming Language :: Python :: 3
Classifier: Programming Language :: Python :: 3 :: Only
Classifier: Programming Language :: Python :: 3.7
Classifier: Programming Language :: Python :: 3.8
Classifier: Programming Language :: Python :: 3.9
Classifier: Programming Language :: Python :: 3.10
Classifier: Programming Language :: Python :: 3.11
Requires-Python: >=3.7
Requires-Dist: aiohttp==3.8.*
Provides-Extra: win
Requires-Dist: pywin32>300; extra == 'win'
